Py_Cep-1.0.5.data/scripts/README.md
Py_Cep-1.0.5.data/scripts/exemplo.py
pycep/__init__.py
Py_Cep-1.0.5.dist-info/LICENSE
Py_Cep-1.0.5.dist-info/METADATA
Py_Cep-1.0.5.dist-info/WHEEL
Py_Cep-1.0.5.dist-info/top_level.txt
Py_Cep-1.0.5.dist-info/RECORD
