Metadata-Version: 2.1
Name: Py-Cep
Version: 1.0.5
Summary: Um simples modulo para obter informacoes de um CEP
Home-page: https://github.com/thomaznathanael/Py-Cep
Author: Thomaz Nathanael
Author-email: thomaznathanael@gmail.com
License: LICENSE
Keywords: cep,json,api,pycep,py-cep
Platform: any
Classifier: Programming Language :: Python
Classifier: Programming Language :: Python :: 2
Classifier: Programming Language :: Python :: 2.7
Classifier: Programming Language :: Python :: 3
Classifier: Programming Language :: Python :: 3.5
Classifier: Development Status :: 4 - Beta
Classifier: Natural Language :: English
Classifier: Environment :: Console
Classifier: Intended Audience :: Developers
Classifier: License :: OSI Approved :: MIT License
Classifier: Operating System :: OS Independent
Classifier: Topic :: Software Development :: Libraries :: Python Modules
Requires-Dist: requests (>=2.9.1)
